spatial_analysis_toolkit/__init__.py
spatial_analysis_toolkit/_version.py
spatial_analysis_toolkit/napari.yaml
spatial_analysis_toolkit/_tests/__init__.py
spatial_analysis_toolkit/_tests/test_dummy.py
spatial_analysis_toolkit/utils/__init__.py
spatial_analysis_toolkit/utils/utils.py
spatial_analysis_toolkit/view/__init__.py
spatial_analysis_toolkit/view/tissuumaps.py
spatial_analysis_toolkit-0.0.6.dist-info/LICENSE
spatial_analysis_toolkit-0.0.6.dist-info/METADATA
spatial_analysis_toolkit-0.0.6.dist-info/WHEEL
spatial_analysis_toolkit-0.0.6.dist-info/entry_points.txt
spatial_analysis_toolkit-0.0.6.dist-info/top_level.txt
spatial_analysis_toolkit-0.0.6.dist-info/RECORD
