Metadata-Version: 2.1
Name: spatial-analysis-toolkit
Version: 0.0.6
Summary: tools for interacting with spatial data
Home-page: https://github.com/kevinyamauchi/spatial-analysis-toolkit
Author: Kevin Yamauchi
Author-email: kevin.yamauchi@gmail.com
License: BSD-3-Clause
Project-URL: Bug Tracker, https://github.com/kevinyamauchi/spatial-analysis-toolkit/issues
Project-URL: Documentation, https://github.com/kevinyamauchi/spatial-analysis-toolkit#README.md
Project-URL: Source Code, https://github.com/kevinyamauchi/spatial-analysis-toolkit
Project-URL: User Support, https://github.com/kevinyamauchi/spatial-analysis-toolkit/issues
Platform: UNKNOWN
Classifier: Development Status :: 2 - Pre-Alpha
Classifier: Intended Audience :: Developers
Classifier: License :: OSI Approved :: BSD License
Classifier: Operating System :: OS Independent
Classifier: Programming Language :: Python
Classifier: Programming Language :: Python :: 3
Classifier: Programming Language :: Python :: 3 :: Only
Classifier: Programming Language :: Python :: 3.8
Classifier: Programming Language :: Python :: 3.9
Classifier: Programming Language :: Python :: 3.10
Classifier: Topic :: Software Development :: Testing
Requires-Python: >=3.8
License-File: LICENSE
Requires-Dist: numpy
Requires-Dist: pandas
Requires-Dist: scikit-image
Requires-Dist: squidpy
Requires-Dist: tifffile (==2022.3.25)
Provides-Extra: dev
Requires-Dist: precommit ; extra == 'dev'
Requires-Dist: pytest ; extra == 'dev'
Requires-Dist: pytest-qt ; extra == 'dev'
Provides-Extra: testing
Requires-Dist: pytest ; extra == 'testing'
Requires-Dist: pytest-cov ; extra == 'testing'
Requires-Dist: tox ; extra == 'testing'
Provides-Extra: tissuumaps
Requires-Dist: TissUUmaps[full] ; extra == 'tissuumaps'
